odoo/addons/product_uom_unece/README.rst
odoo/addons/product_uom_unece/__init__.py
odoo/addons/product_uom_unece/__manifest__.py
odoo/addons/product_uom_unece/data/unece.xml
odoo/addons/product_uom_unece/i18n/product_uom_unece.pot
odoo/addons/product_uom_unece/models/__init__.py
odoo/addons/product_uom_unece/models/product_uom.py
odoo/addons/product_uom_unece/static/description/icon.png
odoo/addons/product_uom_unece/views/product_uom.xml
odoo11_addon_product_uom_unece-11.0.1.1.1.dist-info/METADATA
odoo11_addon_product_uom_unece-11.0.1.1.1.dist-info/WHEEL
odoo11_addon_product_uom_unece-11.0.1.1.1.dist-info/top_level.txt
odoo11_addon_product_uom_unece-11.0.1.1.1.dist-info/RECORD
